qpformat/__init__.py
qpformat/_version.py
qpformat/cli.py
qpformat/core.py
qpformat/file_formats/__init__.py
qpformat/file_formats/errors.py
qpformat/file_formats/fmt_series_folder.py
qpformat/file_formats/registry.py
qpformat/file_formats/series_base.py
qpformat/file_formats/single_base.py
qpformat/file_formats/util.py
qpformat/file_formats/fmts_raw_oah/__init__.py
qpformat/file_formats/fmts_raw_oah/series_raw_oah_hyperspy_hdf5.py
qpformat/file_formats/fmts_raw_oah/series_raw_oah_qpformat_hdf5.py
qpformat/file_formats/fmts_raw_oah/series_raw_oah_tif_zip.py
qpformat/file_formats/fmts_raw_oah/single_raw_oah_qpformat_hdf5.py
qpformat/file_formats/fmts_raw_oah/single_raw_oah_tif.py
qpformat/file_formats/fmts_raw_qlsi/__init__.py
qpformat/file_formats/fmts_raw_qlsi/series_raw_qlsi_qpformat_hdf5.py
qpformat/file_formats/fmts_raw_qlsi/single_raw_qlsi_qpformat_hdf5.py
qpformat/file_formats/fmts_ready/__init__.py
qpformat/file_formats/fmts_ready/series_field_sinogram_meep_hdf5.py
qpformat/file_formats/fmts_ready/series_phase_phasics_tif_zip.py
qpformat/file_formats/fmts_ready/series_phase_qpimage_hdf5.py
qpformat/file_formats/fmts_ready/single_field_phase_numpy_npy.py
qpformat/file_formats/fmts_ready/single_phase_phasics_tif.py
qpformat/file_formats/fmts_ready/single_phase_qpimage_hdf5.py
qpformat-0.14.5.dist-info/LICENSE
qpformat-0.14.5.dist-info/METADATA
qpformat-0.14.5.dist-info/WHEEL
qpformat-0.14.5.dist-info/entry_points.txt
qpformat-0.14.5.dist-info/top_level.txt
qpformat-0.14.5.dist-info/RECORD
