Metadata-Version: 2.2
Name: qpformat
Version: 0.14.5
Summary: library for opening quantitative phase imaging data
Author-email: Paul Müller <dev@craban.de>
License: MIT
Project-URL: Homepage, https://github.com/RI-imaging/qpimage
Keywords: data file format,digital holographic microscopy,quantitative phase imaging
Classifier: Operating System :: OS Independent
Classifier: Programming Language :: Python :: 3
Classifier: Intended Audience :: Science/Research
Requires-Python: <4,>=3.10
License-File: LICENSE
Requires-Dist: h5py>=3.5.0
Requires-Dist: numpy>=1.12.0
Requires-Dist: qpimage>=0.9.1
Requires-Dist: qpretrieve>=0.3.0
Requires-Dist: tifffile>=2020.5.25
